{
  "gamers": [
    {
      "id": 1,
      "pseudo": "Terminator",
      "score": 10,
      "level": "Facile"
    },
    {
      "id": 2,
      "pseudo": "Toto",
      "score": 8,
      "level": "Normal"
    },
    {
      "id": 0,
      "pseudo": "Thipo",
      "score": 0,
      "level": "Facile"
    },
    {
      "id": 71019,
      "pseudo": "tototot",
      "level": "Facile",
      "score": 0,
      "created": "2023-03-29T08:32:11.104Z"
    },
    {
      "id": 87440,
      "pseudo": "pouetosss",
      "level": "Facile",
      "score": 0,
      "created": "2023-03-29T08:33:42.943Z"
    },
    {
      "id": 83946,
      "pseudo": "gg",
      "level": "Facile",
      "score": 0,
      "created": "2023-03-29T08:44:06.223Z"
    },
    {
      "id": 67506,
      "pseudo": "gherjhghg",
      "level": "Facile",
      "score": 0,
      "created": "2023-03-29T08:44:50.678Z"
    },
    {
      "id": 73385,
      "pseudo": "htrhtrh",
      "level": "Facile",
      "score": 0,
      "created": "2023-03-29T08:46:45.079Z"
    },
    {
      "id": 128551,
      "pseudo": "sfsdfsdfsdf",
      "level": "Facile",
      "score": 0,
      "created": "2023-03-29T08:50:26.103Z"
    }
  ]
}